bonchcli/__init__.py
bonchcli/bonchcli.py
bonchcli/config_manager.py
bonchcli/formatting.py
bonchcli-0.0.5.dist-info/METADATA
bonchcli-0.0.5.dist-info/WHEEL
bonchcli-0.0.5.dist-info/entry_points.txt
bonchcli-0.0.5.dist-info/RECORD
