Metadata-Version: 2.4
Name: bonchcli
Version: 0.0.5
Summary: lk.sut.ru console client
Author: Karimullin Arthur
Author-email: KarimullinArthur@disroot.org
Requires-Python: >=3.12,<4.0
Classifier: Programming Language :: Python :: 3
Classifier: Programming Language :: Python :: 3.12
Classifier: Programming Language :: Python :: 3.13
Classifier: Programming Language :: Python :: 3.14
Requires-Dist: bonchapi (==0.0.7)
Requires-Dist: selenium (>=4.28.0,<5.0.0)
Requires-Dist: tomlkit (>=0.13.2,<0.14.0)
